<?xml version="1.0"?><SellOrders><Receipts><RowID>6</RowID><RowAddDateTime>2016-11-14 02:46:22.000000+02:00</RowAddDateTime><RowAddUserNo>1</RowAddUserNo><RowEditDateTime>2016-11-14 02:46:22.000000+02:00</RowEditDateTime><RowEditUserNo>0</RowEditUserNo><ReceiptDirection>1</ReceiptDirection><ReceiptType>1</ReceiptType><ID>1</ID><ReceiptNo>0000000001</ReceiptNo><Time>2016-11-14 02:46:22.000000+02:00</Time><DepotID>1</DepotID><DepotName>merkez</DepotName><EmployeeID>1</EmployeeID><EmployeeName>yusuf aksoy</EmployeeName><AccountID>2</AccountID><AccountCode>0000000002</AccountCode><AccountName>Reis 2 Elektronik</AccountName><BalanceCurrencyNo>2</BalanceCurrencyNo><BalanceCurrencyCode>USD</BalanceCurrencyCode><BalanceCurrencyPrice>3.2588</BalanceCurrencyPrice><Remainder>0</Remainder><CurrencyNo>2</CurrencyNo><CurrencyCode>USD</CurrencyCode><CurrencyPrice>3.2588</CurrencyPrice><TotalAmount>13</TotalAmount><TotalPrice>635.21094382252</TotalPrice><TotalDiscount>0</TotalDiscount><TotalDiscountedPrice>635.21094382252</TotalDiscountedPrice><TotalVATPrice>114.33796988805</TotalVATPrice><NetTotalPrice>749.54891371057</NetTotalPrice><AccountNetTotalPrice>749.54891371057</AccountNetTotalPrice><AccountingAccountNetTotalPrice>0</AccountingAccountNetTotalPrice><Status>0</Status><Explanation></Explanation><AccountingAccountID>0</AccountingAccountID><VatAccountingAccountID>0</VatAccountingAccountID><AccountAccountingAccountID>0</AccountAccountingAccountID><AccountBuyersAccountID>0</AccountBuyersAccountID><AccountSellersAccountID>0</AccountSellersAccountID><BuyersAccountID>0</BuyersAccountID><SellersAccountID>0</SellersAccountID><BuysAccountID>0</BuysAccountID><SellsAccountID>0</SellsAccountID><BuysVatAccountID>0</BuysVatAccountID><SellsVatAccountID>0</SellsVatAccountID><SettingID>1</SettingID></Receipts><ReceiptStocks><RowID>11</RowID><RowAddDateTime>2016-11-14 02:46:25.000000+02:00</RowAddDateTime><RowAddUserNo>1</RowAddUserNo><RowEditDateTime>2016-11-14 02:46:25.000000+02:00</RowEditDateTime><RowEditUserNo>0</RowEditUserNo><ReceiptDirection>1</ReceiptDirection><ReceiptType>1</ReceiptType><ReceiptID>1</ReceiptID><Time>2016-11-14 02:46:25.000000+02:00</Time><AccountID>2</AccountID><ReceiptCurrencyNo>2</ReceiptCurrencyNo><ReceiptCurrencyPrice>3.2588</ReceiptCurrencyPrice><ID>11</ID><StockID>3</StockID><StockCode>0000000003</StockCode><StockName>NF-ANB04 (E90 ANALOG) BMW</StockName><Number></Number><UnitName>Adet</UnitName><Amount>4</Amount><Price>175</Price><CurrencyNo>2</CurrencyNo><CurrencyCode>USD</CurrencyCode><CurrencyPrice>3.2588</CurrencyPrice><Discount>0</Discount><DiscountedPrice>175</DiscountedPrice><DiscountRatio>0</DiscountRatio><DiscountRatio2>0</DiscountRatio2><DiscountRatio3>0</DiscountRatio3><TotalDiscount>0</TotalDiscount><VAT>18</VAT><VATStatus>0</VATStatus><VATPrice>26.694915254237</VATPrice><TotalVATPrice>106.77966101695</TotalVATPrice><WithoutVATPrice>148.30508474576</WithoutVATPrice><TotalWithoutVATPrice>593.22033898305</TotalWithoutVATPrice><NetPrice>175</NetPrice><NetTotalPrice>700</NetTotalPrice><CurrencyTotalWithoutVATPrice>593.22033898305</CurrencyTotalWithoutVATPrice><CurrencyTotalDiscount>0</CurrencyTotalDiscount><CurrencyTotalVATPrice>106.77966101695</CurrencyTotalVATPrice><DepotID>1</DepotID><DepotName>merkez</DepotName><DepotAmount>0</DepotAmount><EmployeeID>1</EmployeeID><EmployeeName>yusuf aksoy</EmployeeName><Explanation></Explanation></ReceiptStocks><ReceiptStocks><RowID>12</RowID><RowAddDateTime>2016-11-14 02:46:25.000000+02:00</RowAddDateTime><RowAddUserNo>1</RowAddUserNo><RowEditDateTime>2016-11-14 02:46:25.000000+02:00</RowEditDateTime><RowEditUserNo>0</RowEditUserNo><ReceiptDirection>1</ReceiptDirection><ReceiptType>1</ReceiptType><ReceiptID>1</ReceiptID><Time>2016-11-14 02:46:25.000000+02:00</Time><AccountID>2</AccountID><ReceiptCurrencyNo>2</ReceiptCurrencyNo><ReceiptCurrencyPrice>3.2588</ReceiptCurrencyPrice><ID>12</ID><StockID>1</StockID><StockCode>0000000001</StockCode><StockName>deneme</StockName><Number></Number><UnitName>Adet</UnitName><Amount>4</Amount><Price>20</Price><CurrencyNo>1</CurrencyNo><CurrencyCode>TL</CurrencyCode><CurrencyPrice>1</CurrencyPrice><Discount>0</Discount><DiscountedPrice>20</DiscountedPrice><DiscountRatio>0</DiscountRatio><DiscountRatio2>0</DiscountRatio2><DiscountRatio3>0</DiscountRatio3><TotalDiscount>0</TotalDiscount><VAT>18</VAT><VATStatus>0</VATStatus><VATPrice>3.0508474576271</VATPrice><TotalVATPrice>12.203389830508</TotalVATPrice><WithoutVATPrice>16.949152542373</WithoutVATPrice><TotalWithoutVATPrice>67.796610169492</TotalWithoutVATPrice><NetPrice>20</NetPrice><NetTotalPrice>80</NetTotalPrice><CurrencyTotalWithoutVATPrice>20.804164161499</CurrencyTotalWithoutVATPrice><CurrencyTotalDiscount>0</CurrencyTotalDiscount><CurrencyTotalVATPrice>3.7447495490697</CurrencyTotalVATPrice><DepotID>1</DepotID><DepotName>merkez</DepotName><DepotAmount>0</DepotAmount><EmployeeID>1</EmployeeID><EmployeeName>yusuf aksoy</EmployeeName><Explanation></Explanation></ReceiptStocks><ReceiptStocks><RowID>13</RowID><RowAddDateTime>2016-11-14 02:46:25.000000+02:00</RowAddDateTime><RowAddUserNo>1</RowAddUserNo><RowEditDateTime>2016-11-14 02:46:25.000000+02:00</RowEditDateTime><RowEditUserNo>0</RowEditUserNo><ReceiptDirection>1</ReceiptDirection><ReceiptType>1</ReceiptType><ReceiptID>1</ReceiptID><Time>2016-11-14 02:46:25.000000+02:00</Time><AccountID>2</AccountID><ReceiptCurrencyNo>2</ReceiptCurrencyNo><ReceiptCurrencyPrice>3.2588</ReceiptCurrencyPrice><ID>13</ID><StockID>2</StockID><StockCode>0000000002</StockCode><StockName>KS-SPY01 ARAÇ DVR</StockName><Number></Number><UnitName>Adet</UnitName><Amount>5</Amount><Price>5</Price><CurrencyNo>2</CurrencyNo><CurrencyCode>USD</CurrencyCode><CurrencyPrice>3.2588</CurrencyPrice><Discount>0</Discount><DiscountedPrice>5</DiscountedPrice><DiscountRatio>0</DiscountRatio><DiscountRatio2>0</DiscountRatio2><DiscountRatio3>0</DiscountRatio3><TotalDiscount>0</TotalDiscount><VAT>18</VAT><VATStatus>0</VATStatus><VATPrice>0.76271186440678</VATPrice><TotalVATPrice>3.8135593220339</TotalVATPrice><WithoutVATPrice>4.2372881355932</WithoutVATPrice><TotalWithoutVATPrice>21.186440677966</TotalWithoutVATPrice><NetPrice>5</NetPrice><NetTotalPrice>25</NetTotalPrice><CurrencyTotalWithoutVATPrice>21.186440677966</CurrencyTotalWithoutVATPrice><CurrencyTotalDiscount>0</CurrencyTotalDiscount><CurrencyTotalVATPrice>3.8135593220339</CurrencyTotalVATPrice><DepotID>1</DepotID><DepotName>merkez</DepotName><DepotAmount>0</DepotAmount><EmployeeID>1</EmployeeID><EmployeeName>yusuf aksoy</EmployeeName><Explanation></Explanation></ReceiptStocks></SellOrders>